algebraic_connectivity_directed/__init__.py
algebraic_connectivity_directed/algebraic_connectivity_directed.py
algebraic_connectivity_directed-0.0.10.dist-info/LICENSE
algebraic_connectivity_directed-0.0.10.dist-info/METADATA
algebraic_connectivity_directed-0.0.10.dist-info/WHEEL
algebraic_connectivity_directed-0.0.10.dist-info/top_level.txt
algebraic_connectivity_directed-0.0.10.dist-info/RECORD
