Metadata-Version: 2.1
Name: algebraic-connectivity-directed
Version: 0.0.10
Summary: Python functions to compute various notions of algebraic connectivity of directed graphs
Home-page: https://github.com/postvakje/algebraic-connectivity-directed
Author: Chai Wah Wu
Author-email: cwwuieee@gmail.com
License: LICENSE
Platform: UNKNOWN
Classifier: Programming Language :: Python :: 3
Classifier: License :: OSI Approved :: Apache Software License
Classifier: Operating System :: OS Independent
Classifier: Topic :: Scientific/Engineering :: Mathematics
Classifier: Topic :: Scientific/Engineering :: Information Analysis
Classifier: Development Status :: 4 - Beta
Classifier: Intended Audience :: Science/Research
Requires-Python: >= 3.5
License-File: LICENSE
Requires-Dist: numpy
Requires-Dist: scipy
Requires-Dist: networkx
Requires-Dist: cvxpy
